{
  "posts": [
    {
      "id": "1",
      "title": "Hello World",
      "content": "This is a mock post.",
      "views": 100
    },
    {
      "id": "2",
      "title": "Nuxt 3 Rocks",
      "content": "This is another mock post.",
      "views": 200
    }
  ],
  "comments": [
    {
      "id": "1",
      "text": "a comment about post 1",
      "postId": "1"
    },
    {
      "id": "2",
      "text": "another comment about post 1",
      "postId": "1"
    }
  ],
  "users": [
    {
      "id": "d565",
      "freeBets": [],
      "address": "dafs",
      "phoneNumber": "daf",
      "city": "dafd",
      "country": "Placeholder",
      "countryISO3": "sfdaftring",
      "postalCode": "daf",
      "phoneCode": "dafd",
      "customerId": "placeholder",
      "firstName": "dfd",
      "lastName": "strfdafing",
      "email": "email1",
      "password": "$2b$10$xlA6vDTCtf7bhZk/ZQmqr.HP7xn/5/v6wIUPGOoFi98dG9ZF7CXTK",
      "dateOfBirth": "2024-06-26T01:55:07.535Z",
      "accountPreferences": {
        "zoneId": "placeholder",
        "languageCode": "daf",
        "preferredFiatCurrency": "dasf",
        "preferredGameLaunchCurrency": "dasf",
        "hidden": true
      },
      "communicationsVerified": false,
      "balances": [
        {
          "currency": "placeholder",
          "currencyPrecision": 0,
          "balance": 0,
          "bonusBalance": 0,
          "vaultBalance": 0
        }
      ],
      "tokenRenewUrl": "eyJhbGciOiJIUzI1NiIsInR5cCI6IkpXVCJ9.eyJpZCI6ImVtYWlsMSIsImlhdCI6MTcxOTQ0NDcwMSwiZXhwIjoxNzE5NTMxMTAxfQ.pDlJjZru051Ie3W_PF6P5xJsOooQjeXQAKTA_gI-EQA",
      "currency": "dasf",
      "mfaLogin": false,
      "mfaWithdrawal": null,
      "mfaStatus": "NOT_SET",
      "mfaReferenceId": null,
      "remind2FA": null,
      "kycData": {
        "idvStatus": "NOT_VERIFIED",
        "poaStatus": "NOT_VERIFIED",
        "displayType": null
      },
      "loginType": "PASSWORD"
    }
  ]
}